{
  "$schema": "https://developer.microsoft.com/json-schemas/fabric/item/report/definition/visualContainer/2.9.0/schema.json",
  "name": "p7_01_card_total",
  "position": {
    "x": 16,
    "y": 92,
    "z": 1,
    "height": 100,
    "width": 200,
    "tabOrder": 1
  },
  "visual": {
    "visualType": "card",
    "query": {
      "queryState": {
        "Values": {
          "projections": [
            {
              "field": {
                "Measure": {
                  "Expression": {
                    "SourceRef": {
                      "Entity": "_Measures"
                    }
                  },
                  "Property": "Total Crimes"
                }
              },
              "queryRef": "_Measures.Total Crimes",
              "nativeQueryRef": "Total Crimes"
            }
          ]
        }
      }
    },
    "visualContainerObjects": {
      "title": [
        {
          "properties": {
            "show": { "expr": { "Literal": { "Value": "true" } } },
            "text": { "expr": { "Literal": { "Value": "'Total Crimes'" } } }
          }
        }
      ]
    },
    "drillFilterOtherVisuals": true
  }
}
